{
  "schemaVersion": 3,
  "title": "Fall 7",
  "caseText": "S: 32-årig kvinna, krampanfall. Ambulans inkommer om 1 minut.\nB: Frisk, medicinfri\nA: Patient som i hemmet plötsligt börjat krampa, bevittnades av sambo. Medvetslös efter kramperna. Ambulans inkom vid andra anfallet med generaliserade kramper, gav 10 mg Stesolid och körde mot akuten.",
  "boxes": {
    "oversikt": {
      "label": "översikt",
      "image": null,
      "ecg": null,
      "blodgas": null,
      "subboxes": [
        {
          "name": "Skyddskläder, handskar, förkläde.",
          "studentAction": "",
          "specialCase": "",
          "tiers": [
            "basic"
          ],
          "critical": false
        },
        {
          "name": "Undersök tecken till hjärtstopp",
          "studentAction": "Finner inget tecken till hjärtstopp",
          "specialCase": "Patienten är medvetslös men andas och har en tydlig puls i carotis.",
          "tiers": [
            "basic"
          ],
          "critical": false
        },
        {
          "name": "Tecken till katastrofal blödning",
          "studentAction": "",
          "specialCase": "Inga tecken till katastrofal blödning.",
          "tiers": [
            "basic"
          ],
          "critical": false
        }
      ]
    },
    "airway": {
      "label": "airway",
      "image": null,
      "ecg": null,
      "blodgas": null,
      "subboxes": [
        {
          "name": "Inspektera ansikte",
          "studentAction": "",
          "specialCase": "Inga tecken på skador",
          "tiers": [
            "basic"
          ],
          "critical": false
        },
        {
          "name": "Inspektera hals",
          "studentAction": "",
          "specialCase": "Inga tecken på skador",
          "tiers": [
            "basic"
          ],
          "critical": false
        },
        {
          "name": "Inspektera munnen och svalg med ficklampa",
          "studentAction": "",
          "specialCase": "Tungbett som inte blöder mycket annars u.a",
          "tiers": [
            "basic",
            "middle"
          ],
          "critical": false
        },
        {
          "name": "Lyssna på andning",
          "studentAction": "",
          "specialCase": "Normala andningsljud, inga tecken på övre luftvägspåverkan",
          "tiers": [
            "basic"
          ],
          "critical": false
        }
      ]
    },
    "breathing": {
      "label": "breathing",
      "image": null,
      "ecg": null,
      "blodgas": null,
      "subboxes": [
        {
          "name": "Beräkna och bedöm andningsfrekvens",
          "studentAction": "",
          "specialCase": "AF 22",
          "tiers": [
            "basic"
          ],
          "critical": false
        },
        {
          "name": "Bedöm saturation (%)",
          "studentAction": "",
          "specialCase": "Saturation 95% med 3 L syrgas med näsgrimma",
          "tiers": [
            "basic"
          ],
          "critical": false
        },
        {
          "name": "Inspektion av bröstkorg, avseende symmetriska andningsrörelser, synliga skador",
          "studentAction": "",
          "specialCase": "Liksidiga andningsrörelser, inga synliga skador.",
          "tiers": [
            "basic"
          ],
          "critical": false
        },
        {
          "name": "Auskultation över lungfälten",
          "studentAction": "",
          "specialCase": "Man hör svaga bilaterala andningsljud.",
          "tiers": [
            "basic"
          ],
          "critical": false
        },
        {
          "name": "Palpation av bröstkorgen",
          "studentAction": "",
          "specialCase": "Ingen smärta vid palpation",
          "tiers": [
            "basic"
          ],
          "critical": false
        }
      ]
    },
    "circulation": {
      "label": "circulation",
      "image": null,
      "ecg": null,
      "blodgas": null,
      "subboxes": [
        {
          "name": "Bestäm hjärtfrekvens",
          "studentAction": "",
          "specialCase": "Hjärtfrekvens 120/min",
          "tiers": [
            "basic"
          ],
          "critical": false
        },
        {
          "name": "Bestäm blodtryck",
          "studentAction": "",
          "specialCase": "BP 135/70",
          "tiers": [
            "basic"
          ],
          "critical": false
        },
        {
          "name": "Bestäm kapillär återfyllnadstid",
          "studentAction": "",
          "specialCase": "Kapillär återfyllnad <2s",
          "tiers": [
            "basic"
          ],
          "critical": false
        },
        {
          "name": "Bedömning av perifera pulsationer bilateralt",
          "studentAction": "",
          "specialCase": "Liksidiga pulsar i radialis/femoralis",
          "tiers": [
            "basic"
          ],
          "critical": false
        },
        {
          "name": "Bedömning av perifer cirkulation",
          "studentAction": "",
          "specialCase": "Normalt",
          "tiers": [
            "basic"
          ],
          "critical": false
        },
        {
          "name": "Palpation av buk, becken och lårben",
          "studentAction": "",
          "specialCase": "Inspektion/palpation över buk/bäcken/lårben u.a.",
          "tiers": [
            "basic"
          ],
          "critical": false
        },
        {
          "name": "Ordination av venösa infarter",
          "studentAction": "Ordinerar grov (minst grön) infart",
          "specialCase": "",
          "tiers": [
            "basic"
          ],
          "critical": false
        },
        {
          "name": "Ordination av blodgas ± glukos",
          "studentAction": "",
          "specialCase": "",
          "tiers": [
            "basic"
          ],
          "critical": false
        }
      ]
    },
    "disability": {
      "label": "disability",
      "image": null,
      "ecg": null,
      "blodgas": null,
      "subboxes": [
        {
          "name": "Bedömning av medvetandegrad (RLS/GCS)",
          "studentAction": "Ska tolka RLS 4",
          "specialCase": "Svarar inte på tilltal. Vid smärtstimulering lokaliserar patienten smärtan (RLS 4)",
          "tiers": [
            "basic",
            "middle"
          ],
          "critical": false
        },
        {
          "name": "Undersökning av ögon",
          "studentAction": "",
          "specialCase": "Pupiller medelvida, centrerade med normal ljusreaktion",
          "tiers": [
            "basic"
          ],
          "critical": false
        },
        {
          "name": "Undersökning av grov kraft i armar och ben",
          "studentAction": "",
          "specialCase": "Grovmotorik och sensorik u.a (reagerar lite när man nyper på armarna).",
          "tiers": [
            "basic"
          ],
          "critical": false
        },
        {
          "name": "Undersökning av sensorik armar och ben",
          "studentAction": "",
          "specialCase": "Grovmotorik och sensorik u.a (reagerar lite när man nyper på armarna).",
          "tiers": [
            "basic"
          ],
          "critical": false
        },
        {
          "name": "Ordination av kapillär glukos",
          "studentAction": "",
          "specialCase": "Glukos kommer på blodgasen",
          "tiers": [
            "basic"
          ],
          "critical": false
        }
      ]
    },
    "exposure": {
      "label": "exposure",
      "image": null,
      "ecg": null,
      "blodgas": null,
      "subboxes": [
        {
          "name": "bestämning av kroppstemperatur",
          "studentAction": "Ordinerar varma täcken",
          "specialCase": "Temperatur 35,5°",
          "tiers": [
            "basic"
          ],
          "critical": false
        },
        {
          "name": "inspektion av kroppens fram- och baksida",
          "studentAction": "",
          "specialCase": "Undersökning med stockvändning u.a.",
          "tiers": [
            "basic"
          ],
          "critical": false
        }
      ]
    },
    "blodgas": {
      "label": "blodgas",
      "image": null,
      "ecg": null,
      "blodgas": {
        "schema": "blodgas-lab.v1",
        "createdAt": "2026-02-02T19:11:08.096Z",
        "settings": {
          "baroKpa": 101.3,
          "comment": "",
          "showRef": "on",
          "editTemplate": "off"
        },
        "sections": [
          {
            "id": "calc",
            "label": "Beräknade värden",
            "rows": [
              {
                "id": "chco3st",
                "name": "cHCO₃⁻ (P,st)c",
                "value": "19",
                "unit": "mmol/L",
                "refLow": 22,
                "refHigh": 27
              },
              {
                "id": "chco3",
                "name": "cHCO₃⁻ (P)c",
                "value": "18",
                "unit": "mmol/L",
                "refLow": 22,
                "refHigh": 26
              },
              {
                "id": "abec",
                "name": "ABEc",
                "value": "-8",
                "unit": "mmol/L",
                "refLow": -3,
                "refHigh": 3
              },
              {
                "id": "p50c",
                "name": "p50c",
                "value": "3,85",
                "unit": "kPa",
                "refLow": 3.3,
                "refHigh": 3.9
              }
            ]
          },
          {
            "id": "abg",
            "label": "Blodgasvärden",
            "rows": [
              {
                "id": "ph",
                "name": "pH",
                "value": "7,24",
                "unit": "",
                "refLow": null,
                "refHigh": null
              },
              {
                "id": "pco2",
                "name": "pCO₂",
                "value": "6,2",
                "unit": "kPa",
                "refLow": null,
                "refHigh": null
              },
              {
                "id": "po2",
                "name": "pO₂",
                "value": "10,2",
                "unit": "kPa",
                "refLow": null,
                "refHigh": null
              },
              {
                "id": "so2",
                "name": "sO₂",
                "value": "95",
                "unit": "%",
                "refLow": null,
                "refHigh": null
              }
            ]
          },
          {
            "id": "elec",
            "label": "Elektrolytvärden",
            "rows": [
              {
                "id": "na",
                "name": "cNa⁺",
                "value": "139",
                "unit": "mmol/L",
                "refLow": 137,
                "refHigh": 145
              },
              {
                "id": "k",
                "name": "cK⁺",
                "value": "5,3",
                "unit": "mmol/L",
                "refLow": 3.2,
                "refHigh": 4.2
              },
              {
                "id": "cl",
                "name": "cCl⁻",
                "value": "102",
                "unit": "mmol/L",
                "refLow": 98,
                "refHigh": 106
              },
              {
                "id": "ca",
                "name": "cCa²⁺",
                "value": "1,15",
                "unit": "mmol/L",
                "refLow": null,
                "refHigh": null
              },
              {
                "id": "ca74",
                "name": "cCa²⁺(7.4)c",
                "value": "1,17",
                "unit": "mmol/L",
                "refLow": 1.16,
                "refHigh": 1.35
              }
            ]
          },
          {
            "id": "met",
            "label": "Metabolitvärden",
            "rows": [
              {
                "id": "glu",
                "name": "cGlu",
                "value": "8,1",
                "unit": "mmol/L",
                "refLow": 4.2,
                "refHigh": 6.3
              },
              {
                "id": "lac",
                "name": "cLac",
                "value": "6,2",
                "unit": "mmol/L",
                "refLow": 0.5,
                "refHigh": 1.6
              }
            ]
          },
          {
            "id": "ox",
            "label": "Oximetervärden",
            "rows": [
              {
                "id": "hb",
                "name": "ctHb",
                "value": "145",
                "unit": "g/L",
                "refLow": null,
                "refHigh": null
              },
              {
                "id": "fo2",
                "name": "FO₂Hb",
                "value": "95",
                "unit": "%",
                "refLow": 95,
                "refHigh": 99
              },
              {
                "id": "fco",
                "name": "FCOHb",
                "value": "0,7",
                "unit": "%",
                "refLow": 0.5,
                "refHigh": 2.5
              },
              {
                "id": "fhhb",
                "name": "FHHb",
                "value": "4,5",
                "unit": "%",
                "refLow": 1,
                "refHigh": 5
              },
              {
                "id": "fmet",
                "name": "FMetHb",
                "value": "0,6",
                "unit": "%",
                "refLow": 0.4,
                "refHigh": 1.5
              }
            ]
          }
        ]
      },
      "subboxes": [
        {
          "name": "Undersöker och tolkar acidemi/alkalemi",
          "studentAction": "Identifierar acidemi",
          "specialCase": "",
          "tiers": [
            "basic"
          ],
          "critical": false
        },
        {
          "name": "Respiratorisk/metabol genes, kompensation",
          "studentAction": "Identifierar kombinerad respiratorisk och metabol acidos",
          "specialCase": "",
          "tiers": [
            "basic",
            "middle"
          ],
          "critical": false
        },
        {
          "name": "Övriga värden (Na, K, Hb, Cl, Ca, glukos, laktat, FCOHb",
          "studentAction": "Identifierar tydligt förhöjt laktat, förenligt med postiktalt tillstånd efter generaliserat epileptiskt anfall. Ska spontant nämna glukosbedömning",
          "specialCase": "",
          "tiers": [
            "basic",
            "middle"
          ],
          "critical": false
        }
      ]
    },
    "ekg": {
      "label": "ekg",
      "image": null,
      "ecg": {
        "schema": "ekg-lab.v1",
        "createdAt": "2026-02-02T19:13:10.907Z",
        "settings": {
          "template": "",
          "rhythm": "Sinusrytm",
          "age": 66,
          "sex": "kvinna",
          "hr": 75,
          "speed": 50,
          "gain": 10,
          "noise": 0.03,
          "wander": 0.06,
          "prMs": 160,
          "qrsMs": 90,
          "qtMs": 400,
          "axisDeg": 60,
          "linkAxis": "off",
          "showMeasures": "on",
          "ectopyType": "off",
          "ectopyPerMin": 0,
          "ectopyCoupling": "mid",
          "ectopyPattern": "random",
          "pqrst": {
            "P": {
              "amp": 0.12,
              "width": 0.03
            },
            "Q": {
              "amp": -0.15,
              "width": 0.008
            },
            "R": {
              "amp": 1,
              "width": 0.006
            },
            "S": {
              "amp": -0.25,
              "width": 0.01
            },
            "T": {
              "amp": 0.35,
              "width": 0.06,
              "tailAmp": 0,
              "tailWidth": 0.05
            }
          },
          "leads": {
            "aVL": {
              "scale": 1,
              "invert": false,
              "st": 0,
              "pqrst": {},
              "__leadName": "aVL"
            },
            "I": {
              "scale": 1,
              "invert": false,
              "st": 0,
              "pqrst": {},
              "__leadName": "I"
            },
            "-aVR": {
              "scale": 1,
              "invert": false,
              "st": 0,
              "pqrst": {},
              "__leadName": "-aVR"
            },
            "II": {
              "scale": 1,
              "invert": false,
              "st": 0,
              "pqrst": {},
              "__leadName": "II"
            },
            "aVF": {
              "scale": 1,
              "invert": false,
              "st": 0,
              "pqrst": {},
              "__leadName": "aVF"
            },
            "III": {
              "scale": 1,
              "invert": false,
              "st": 0,
              "pqrst": {},
              "__leadName": "III"
            },
            "V1": {
              "scale": 0.7,
              "invert": true,
              "st": 0,
              "pqrst": {},
              "__leadName": "V1"
            },
            "V2": {
              "scale": 0.8,
              "invert": true,
              "st": 0,
              "pqrst": {
                "T": {
                  "amp": -0.2,
                  "width": 0.06,
                  "tailAmp": 0,
                  "tailWidth": 0.05
                }
              },
              "__leadName": "V2"
            },
            "V3": {
              "scale": 0.95,
              "invert": false,
              "st": 0,
              "pqrst": {},
              "__leadName": "V3"
            },
            "V4": {
              "scale": 1.15,
              "invert": false,
              "st": 0,
              "pqrst": {},
              "__leadName": "V4"
            },
            "V5": {
              "scale": 1,
              "invert": false,
              "st": 0,
              "pqrst": {},
              "__leadName": "V5"
            },
            "V6": {
              "scale": 0.85,
              "invert": false,
              "st": 0,
              "pqrst": {},
              "__leadName": "V6"
            }
          }
        }
      },
      "blodgas": null,
      "subboxes": [
        {
          "name": "Frekvens",
          "studentAction": "",
          "specialCase": "",
          "tiers": [
            "basic"
          ],
          "critical": false
        },
        {
          "name": "Rytm",
          "studentAction": "",
          "specialCase": "",
          "tiers": [
            "basic"
          ],
          "critical": false
        },
        {
          "name": "QRS",
          "studentAction": "",
          "specialCase": "",
          "tiers": [
            "basic"
          ],
          "critical": false
        },
        {
          "name": "STT-sträcka",
          "studentAction": "",
          "specialCase": "",
          "tiers": [
            "basic"
          ],
          "critical": false
        },
        {
          "name": "QT-tid",
          "studentAction": "",
          "specialCase": "",
          "tiers": [
            "basic"
          ],
          "critical": false
        }
      ]
    },
    "handlaggning": {
      "label": "handläggning",
      "image": null,
      "ecg": null,
      "blodgas": null,
      "subboxes": [
        {
          "name": "Bedömer behov av riktad klinisk undersökning (Ultraljud, PR, Nackstelhet)",
          "studentAction": "",
          "specialCase": "",
          "tiers": [
            "basic"
          ],
          "critical": false
        },
        {
          "name": "Initierar adekvat behandling",
          "studentAction": "Ska ordagrannt beskriva “generella kramper” → ska inom 60 s från symtomdebut spontant ordinera ≥10 mg Diazepam/Stesolid → detta stillar kramper",
          "specialCase": "Nu ska patienten börja krampa igen med generella skakningar (Du ska säga “Patienten börjar krampa, med skakningar i hela kroppen”).",
          "tiers": [
            "basic"
          ],
          "critical": false
        },
        {
          "name": "Re-evaluerar (Övervakar och utvärderar effekter av åtgärder)",
          "studentAction": "Ska spontant göra en reevaluering där man ska identifera en hypoventilering (<10) → Ska ordinera ventilation med mask och blåsa 15 L syrgas\nIdentifierar urinavgång som kramprelaterat",
          "specialCase": "Du ser att patienten har en spontan urinavgång",
          "tiers": [
            "basic"
          ],
          "critical": true
        }
      ]
    },
    "signout": {
      "label": "signout",
      "image": null,
      "ecg": null,
      "blodgas": null,
      "subboxes": [
        {
          "name": "Formulerar arbetsdiagnos",
          "studentAction": "Identifierar krampanfall utan känd epilepsi",
          "specialCase": "",
          "tiers": [
            "basic"
          ],
          "critical": false
        },
        {
          "name": "Planerar vidare behandling",
          "studentAction": "Ordinerar CT-hjärna som nästa steg i utredning",
          "specialCase": "",
          "tiers": [
            "basic",
            "middle"
          ],
          "critical": false
        },
        {
          "name": "Bedömer övervakningsbehov och vårdnivå",
          "studentAction": "Kontaktar narkos för ev. intubationsbehov och inläggning på IVA",
          "specialCase": "",
          "tiers": [
            "basic",
            "middle"
          ],
          "critical": false
        }
      ]
    }
  }
}